QRegexEditor-0.5.3.dist-info/DESCRIPTION.rst
QRegexEditor-0.5.3.dist-info/METADATA
QRegexEditor-0.5.3.dist-info/RECORD
QRegexEditor-0.5.3.dist-info/WHEEL
QRegexEditor-0.5.3.dist-info/entry_points.txt
QRegexEditor-0.5.3.dist-info/metadata.json
QRegexEditor-0.5.3.dist-info/top_level.txt
qregexeditor/__init__.py
qregexeditor/_hooks.py
qregexeditor/qt.py
qregexeditor/api/__init__.py
qregexeditor/api/editor.py
qregexeditor/api/match_highlighter.py
qregexeditor/api/quick_ref.py
qregexeditor/api/forms/__init__.py
qregexeditor/api/forms/editor_ui.py
qregexeditor/api/forms/quick_ref_ui.py
qregexeditor/app/__init__.py
qregexeditor/app/main.py
qregexeditor/app/main_window.py
qregexeditor/app/settings.py
qregexeditor/app/forms/__init__.py
qregexeditor/app/forms/main_window_ui.py
qregexeditor/app/forms/qregexeditor_rc.py
